vEMreg/FiReTiTiLiB.jar
vEMreg/__init__.py
vEMreg/vEMreg.py
vEMreg/lib/FiReTiTiCoreJava.jar
vEMreg/lib/JTransforms-3.1-with-dependencies.jar
vEMreg/lib/Jama-1.0.2.jar
vEMreg/lib/bioformats_package.jar
vEMreg/lib/common-image-3.8.1.jar
vEMreg/lib/common-io-3.8.1.jar
vEMreg/lib/common-lang-3.8.1.jar
vEMreg/lib/commons-math-1.0.jar
vEMreg/lib/imageio-core-3.8.1.jar
vEMreg/lib/imageio-metadata-3.8.1.jar
vEMreg/lib/imageio-tiff-3.9.0-20220504.163059-23.jar
vEMreg/lib/imagescience.jar
vEMreg/lib/jai_codec.jar
vEMreg/lib/jai_core.jar
vEMreg/lib/java-image-scaling-0.8.6.jar
vEMreg-0.1.dist-info/METADATA
vEMreg-0.1.dist-info/WHEEL
vEMreg-0.1.dist-info/entry_points.txt
vEMreg-0.1.dist-info/top_level.txt
vEMreg-0.1.dist-info/RECORD
